LICENSE
README.md
setup.py
maxipago/__init__.py
maxipago/client.py
maxipago/exceptions.py
maxipago/managers/__init__.py
maxipago/managers/base.py
maxipago/managers/card.py
maxipago/managers/customer.py
maxipago/managers/transaction.py
maxipago/managers/payment/__init__.py
maxipago/managers/payment/payment.py
maxipago/managers/payment/recurring.py
maxipago/managers/recurring/__init__.py
maxipago/managers/recurring/recurring.py
maxipago/requesters/__init__.py
maxipago/requesters/base.py
maxipago/requesters/card.py
maxipago/requesters/customer.py
maxipago/requesters/transaction.py
maxipago/requesters/payment/__init__.py
maxipago/requesters/payment/payment.py
maxipago/requesters/recurring/__init__.py
maxipago/requesters/recurring/recurring.py
maxipago/resources/__init__.py
maxipago/resources/base.py
maxipago/resources/card.py
maxipago/resources/customer.py
maxipago/resources/payment.py
maxipago/resources/recurring.py
maxipago/resources/transaction.py
maxipago/utils/__init__.py
maxipago/utils/payment_processors.py
maxipago/utils/xml.py
maxipago_sdk_iesde.egg-info/PKG-INFO
maxipago_sdk_iesde.egg-info/SOURCES.txt
maxipago_sdk_iesde.egg-info/dependency_links.txt
maxipago_sdk_iesde.egg-info/requires.txt
maxipago_sdk_iesde.egg-info/top_level.txt