Metadata-Version: 1.1
Name: maxipago-sdk-iesde
Version: 1.3.2
Summary: SDK python
Home-page: https://github.com/iesde/sdk-python
Author: Stored
Author-email: contato@stored.com.br
License: MIT
Platform: UNKNOWN
Classifier: Topic :: Utilities
